[
  {
    "title": "5 AI Agent Terms You Need to Know",
    "filename": "2026-07-16-5-ai-agent-terms-you-need-to-know.html",
    "date": "2026-07-16",
    "channel": "",
    "duration": "11m7s",
    "preview": "Learn more about AI Agents here → https://ibm.biz/~dXkrYnDwR Frontier AI agents rely on more than just large language mo"
  },
  {
    "title": "AI Has Changed Completely: Here's What Matters in 2026",
    "filename": "2026-07-16-ai-has-changed-completely-heres-what-matters-in-2026.html",
    "date": "2026-07-16",
    "channel": "",
    "duration": "22m23s",
    "preview": "30 of the best AI Prompts:* https://clickhubspot.com/tjrh More from Futurepedia: Join the Skill Leap AI education platfo"
  },
  {
    "title": "AI Tool 2026 (Modern Strategies)",
    "filename": "2026-07-16-ai-tool-2026-modern-strategies.html",
    "date": "2026-07-16",
    "channel": "",
    "duration": "9m57s",
    "preview": "AI Tool 2026 optimizes complex content generation workflows and automates repetitive backend configurations for technica"
  },
  {
    "title": "Hermes Agent Just Got 10X Better (4 Insane NEW Features)",
    "filename": "2026-07-16-hermes-agent-just-got-10x-better-4-insane-new-features.html",
    "date": "2026-07-16",
    "channel": "",
    "duration": "10m38s",
    "preview": "Hermes AI Agent Just Got 10X Better (4 Insane NEW Features). Join our FREE community: ..."
  },
  {
    "title": "How to Actually Use AI Tools in 2026 (Full Guide)",
    "filename": "2026-07-16-how-to-actually-use-ai-tools-in-2026-full-guide.html",
    "date": "2026-07-16",
    "channel": "",
    "duration": "12m40s",
    "preview": "Go from ABSOLUTE ZERO to using AI like the people who do this for a living   ..."
  },
  {
    "title": "Pydantic AI 2.0: The New Best Way to Build AI Agents is Composing Capabilities",
    "filename": "2026-07-16-pydantic-ai-20-the-new-best-way-to-build-ai.html",
    "date": "2026-07-16",
    "channel": "",
    "duration": "15m1s",
    "preview": "The new best way to build AI agents is to compose capabilities, instead of every agent being a unorganized pile of tools"
  },
  {
    "title": "The AI Tools You'll ACTUALLY Use in 2026!",
    "filename": "2026-07-16-the-ai-tools-youll-actually-use-in-2026.html",
    "date": "2026-07-16",
    "channel": "",
    "duration": "12m56s",
    "preview": "Get your free Make Pro subscription here* – https://www.make.com/en?"
  },
  {
    "title": "The Easiest FREE AI Tools for Beginners in 2026",
    "filename": "2026-07-16-the-easiest-free-ai-tools-for-beginners-in-2026.html",
    "date": "2026-07-16",
    "channel": "",
    "duration": "8m13s",
    "preview": "Go from ABSOLUTE ZERO to using AI like the people who do this for a living   ..."
  },
  {
    "title": "Why AI Agents are either the best or worst thing we’ve ever built",
    "filename": "2026-07-16-why-ai-agents-are-either-the-best-or-worst-thing.html",
    "date": "2026-07-16",
    "channel": "",
    "duration": "20m19s",
    "preview": "I built an AI agent. She opened a shop selling novelty mugs, emailed a journalist without being asked, and then leaked o"
  },
  {
    "title": "You’re Not Behind (Yet): Learn AI Agents in 13 Minutes",
    "filename": "2026-07-16-youre-not-behind-yet-learn-ai-agents-in-13-minutes.html",
    "date": "2026-07-16",
    "channel": "",
    "duration": "13m10s",
    "preview": "... https://www.sandeepswadia.com/newsletter Most people still use AI like a better search box, but the real shift is AI"
  }
]